cassowary/__init__.py
cassowary/edit_info.py
cassowary/error.py
cassowary/expression.py
cassowary/simplex_solver.py
cassowary/tableau.py
cassowary/utils.py
cassowary-0.5.2.dist-info/AUTHORS
cassowary-0.5.2.dist-info/LICENSE
cassowary-0.5.2.dist-info/METADATA
cassowary-0.5.2.dist-info/WHEEL
cassowary-0.5.2.dist-info/top_level.txt
cassowary-0.5.2.dist-info/RECORD
